scrubdash/__init__.py
scrubdash/__main__.py
scrubdash/create_config.py
scrubdash/asyncio_server/__init__.py
scrubdash/asyncio_server/asyncio_server.py
scrubdash/asyncio_server/filesystem.py
scrubdash/asyncio_server/networking.py
scrubdash/asyncio_server/notification.py
scrubdash/asyncio_server/session.py
scrubdash/cfgs/config.yaml.example
scrubdash/dash_server/__init__.py
scrubdash/dash_server/app.py
scrubdash/dash_server/dash_server.py
scrubdash/dash_server/dataframe.py
scrubdash/dash_server/images.py
scrubdash/dash_server/networking.py
scrubdash/dash_server/apps/__init__.py
scrubdash/dash_server/apps/about_page.py
scrubdash/dash_server/apps/graphs_page.py
scrubdash/dash_server/apps/history_page.py
scrubdash/dash_server/apps/labels_page.py
scrubdash/dash_server/apps/main_page.py
scrubdash/dash_server/apps/navbar.py
scrubdash/dash_server/assets/scrubdash-logo.png
scrubdash/dash_server/assets/styles.css
scrubdash/dash_server/assets/Roboto/LICENSE.txt
scrubdash/dash_server/assets/Roboto/Roboto-Black.ttf
scrubdash/dash_server/assets/Roboto/Roboto-BlackItalic.ttf
scrubdash/dash_server/assets/Roboto/Roboto-Bold.ttf
scrubdash/dash_server/assets/Roboto/Roboto-BoldItalic.ttf
scrubdash/dash_server/assets/Roboto/Roboto-Italic.ttf
scrubdash/dash_server/assets/Roboto/Roboto-Light.ttf
scrubdash/dash_server/assets/Roboto/Roboto-LightItalic.ttf
scrubdash/dash_server/assets/Roboto/Roboto-Medium.ttf
scrubdash/dash_server/assets/Roboto/Roboto-MediumItalic.ttf
scrubdash/dash_server/assets/Roboto/Roboto-Regular.ttf
scrubdash/dash_server/assets/Roboto/Roboto-Thin.ttf
scrubdash/dash_server/assets/Roboto/Roboto-ThinItalic.ttf
scrubdash-0.0.1.dist-info/LICENSE
scrubdash-0.0.1.dist-info/METADATA
scrubdash-0.0.1.dist-info/WHEEL
scrubdash-0.0.1.dist-info/entry_points.txt
scrubdash-0.0.1.dist-info/top_level.txt
scrubdash-0.0.1.dist-info/RECORD
