Metadata-Version: 2.1
Name: scrubdash
Version: 0.0.1
Summary: Code for ScrubDash: Dashboard for organizing, visualizing, and analyzing images coming in from a ScrubCam(s).
Home-page: https://github.com/icr-ctl/scrubdash
Author: Conservation Technology Lab at the San Diego Zoo Wildlife Alliance
License: MIT
Platform: UNKNOWN
Classifier: Programming Language :: Python :: 3
Classifier: License :: OSI Approved :: MIT License
Classifier: Development Status :: 2 - Pre-Alpha
Classifier: Topic :: Scientific/Engineering
Requires-Python: >=3.7
License-File: LICENSE
Requires-Dist: aiosmtplib
Requires-Dist: dash
Requires-Dist: dash-daq
Requires-Dist: dash-bootstrap-components
Requires-Dist: dash-core-components
Requires-Dist: dash-html-components
Requires-Dist: numpy
Requires-Dist: pandas
Requires-Dist: Pillow
Requires-Dist: plotly
Requires-Dist: PyYAML
